huaweicloudsdkmsgsms/__init__.py
huaweicloudsdkmsgsms/v2/__init__.py
huaweicloudsdkmsgsms/v2/msgsms_async_client.py
huaweicloudsdkmsgsms/v2/msgsms_client.py
huaweicloudsdkmsgsms/v2/model/__init__.py
huaweicloudsdkmsgsms/v2/model/api_template_variable.py
huaweicloudsdkmsgsms/v2/model/create_app_request.py
huaweicloudsdkmsgsms/v2/model/create_app_response.py
huaweicloudsdkmsgsms/v2/model/create_signature_request.py
huaweicloudsdkmsgsms/v2/model/create_signature_response.py
huaweicloudsdkmsgsms/v2/model/create_template_request.py
huaweicloudsdkmsgsms/v2/model/create_template_response.py
huaweicloudsdkmsgsms/v2/model/delete_signature_request.py
huaweicloudsdkmsgsms/v2/model/delete_signature_response.py
huaweicloudsdkmsgsms/v2/model/delete_template_request.py
huaweicloudsdkmsgsms/v2/model/delete_template_response.py
huaweicloudsdkmsgsms/v2/model/enable_signature_request.py
huaweicloudsdkmsgsms/v2/model/enable_signature_response.py
huaweicloudsdkmsgsms/v2/model/list_app_details_request.py
huaweicloudsdkmsgsms/v2/model/list_app_details_response.py
huaweicloudsdkmsgsms/v2/model/list_send_country_details_request.py
huaweicloudsdkmsgsms/v2/model/list_send_country_details_response.py
huaweicloudsdkmsgsms/v2/model/list_signature_details_request.py
huaweicloudsdkmsgsms/v2/model/list_signature_details_response.py
huaweicloudsdkmsgsms/v2/model/list_template_details_request.py
huaweicloudsdkmsgsms/v2/model/list_template_details_response.py
huaweicloudsdkmsgsms/v2/model/list_template_varilable_details_request.py
huaweicloudsdkmsgsms/v2/model/list_template_varilable_details_response.py
huaweicloudsdkmsgsms/v2/model/show_app_count_request.py
huaweicloudsdkmsgsms/v2/model/show_app_count_response.py
huaweicloudsdkmsgsms/v2/model/show_app_request.py
huaweicloudsdkmsgsms/v2/model/show_app_response.py
huaweicloudsdkmsgsms/v2/model/show_signature_file_request.py
huaweicloudsdkmsgsms/v2/model/show_signature_file_response.py
huaweicloudsdkmsgsms/v2/model/show_signature_request.py
huaweicloudsdkmsgsms-3.1.184.dist-info/METADATA
huaweicloudsdkmsgsms-3.1.184.dist-info/WHEEL
huaweicloudsdkmsgsms-3.1.184.dist-info/licenses/LICENSE
huaweicloudsdkmsgsms-3.1.184.dist-info/RECORD
